Lab 5_3/ALU.v
//CO224 - Computer Architecture
//Lab 5_1   : 8-bit ALU

// module testbed;

// 	// Declare variables for stimulating input
// 	reg [2:0] ALUOP;                        //3 bit register for operations
//     reg signed [7:0] OPERAND1,OPERAND2;    //8 bit registers for Data1 and Data2
//     wire signed [7:0] ALURESULT;           //8 bit register to store result

//     // instantiation of ALU
//     alu a1( OPERAND1,OPERAND2,ALURESULT,ALUOP);


//     //Monitor changes in ALURESULT and print once a ALUOP change happens

//     initial begin
//         $monitor($time," Select: %d     Data1: %d    Data2: %d     result : %d", ALUOP, OPERAND1,  OPERAND2,  ALURESULT);
   
//         assign OPERAND1 = 8'd15;     // provide random input to check
//         assign OPERAND2 = 8'd22;
//         assign ALUOP=3'd0;
// 	    #5 
//         assign OPERAND1 = 8'd3;
//         assign OPERAND2 = 8'd5;
//         assign ALUOP=3'd1;
// 	    #5
//         assign OPERAND1 = 8'd3;
//         assign OPERAND2 = 8'd5;
//         assign ALUOP=3'd2;
	    
// 	    #5
//         assign OPERAND1 = 8'd4;
//         assign OPERAND2 = 8'd5;
//         assign ALUOP=3'd3;
//         #5 
//         assign OPERAND1 = 8'd115;
//         assign OPERAND2 = 8'd232;
//         assign ALUOP=3'd0;
// 	    #5
//         assign OPERAND1 = 8'd7;
//         assign OPERAND2 = 8'd0;
//         assign ALUOP=3'd3;
//         #5 
//         assign OPERAND1 = 8'd2;
//         assign OPERAND2 = 8'd4;
//         assign ALUOP=3'd2;
// 	    #5
//         assign OPERAND1 = 8'd156;
//         assign OPERAND2 = 8'd20;
//         assign ALUOP=3'd1; 
//         #5
//         assign OPERAND1 = 8'd6;
//         assign OPERAND2 = 8'd20;
//         assign ALUOP=3'd3; 
//     end

// endmodule


//alu module
module alu(DATA1, DATA2, RESULT, SELECT, ZERO) ;

	// Port declarations
	output signed [7:0] RESULT;   //8 bit wire to output the result
	input signed [7:0] DATA1,DATA2;    //8 bit input data
    input [2:0] SELECT;         //a code for operations
    reg [7:0] out;              //a temporary register to store results
    output ZERO;

    wire signed [7:0] RESULT1,RESULT2,RESULT3,RESULT4; // 7 bit wires to store result according to the operation

    // Do all the operations on DATA1 and DATA2
    Forward f( DATA2,RESULT1);          //forward DATA2 data to RESULT1
    Add a2(DATA1,DATA2,RESULT2,ZERO);   //add two operands
    And a3(DATA1,DATA2,RESULT3);        //bitwise ANDing
    Or o1(DATA1,DATA2,RESULT4);         //bitwise ORing

    always @(SELECT,RESULT1,RESULT2,RESULT3,RESULT4) begin
        case (SELECT)
 		    3'd0 :   out= RESULT1;   // store Forward operation results in register out
 		    3'd1 :   out= RESULT2;   // store Add operation results in register out
 		    3'd2 :   out= RESULT3;   // store And operation results in register out
		    3'd3 :   out= RESULT4;   // store Or operation results in register out
	    endcase
    end
    //store results in to the output RESULT
    assign RESULT = out;

endmodule



//forward module
module Forward(DATA2,RESULT);
    // module to pass the data as it is
    // Port declarations
    output [7:0] RESULT;
    input [7:0] DATA2;
    
    //store the result in to the output
    assign  #1 RESULT = DATA2;

endmodule


//add module
module Add(DATA1,DATA2,RESULT,ZERO);
    // module to perform ADD operation
    // Port declarations
    output signed [7:0] RESULT;
    output reg ZERO;
    input signed [7:0] DATA1,DATA2;

    //store the result in to the output
    assign #2 RESULT= (DATA1+DATA2);

    always @(RESULT) begin
        ZERO=1'b0;
        if(RESULT==8'd0) begin
            ZERO=1'b1;
        end
    end

endmodule

//add module
module And(DATA1,DATA2,RESULT);
    // module to perform AND operation
    // Port declarations
    output [7:0] RESULT;
    input [7:0] DATA1,DATA2;
   
    //store the result in to the output
    assign  #1 RESULT= DATA1 & DATA2;

endmodule


//forward module
module Or(DATA1,DATA2,RESULT);
    // module to perform OR operation
    // Port declarations
    output [7:0] RESULT;
    input [7:0] DATA1,DATA2;
    
    //store the result in to the output
    assign  #1 RESULT = DATA2 | DATA1;

endmodule

Lab 5_3/REG.v
//CO224 - Computer Architecture
//Lab 5_2 : 8x8 register

// module reg_file_tb;
    
//     reg [7:0] WRITEDATA;
//     reg [2:0] WRITEREG, READREG1, READREG2;
//     reg CLK, RESET, WRITEENABLE; 
//     wire signed [7:0] REGOUT1, REGOUT2;
    
//     reg_file myregisters(WRITEDATA, REGOUT1, REGOUT2, WRITEREG, READREG1, READREG2, WRITEENABLE, CLK, RESET);
    
//     initial
//     begin
//         CLK = 1'b1;
        
//         // generate files needed to plot the waveform using GTKWave
//         $dumpfile("reg_file_wavedata.vcd");
// 		$dumpvars(0, reg_file_tb);
        
//         // assign values with time to input signals to see output 
//         RESET = 1'b0;
//         WRITEENABLE = 1'b0;
        
//         #5
//         RESET = 1'b1;
//         READREG1 = 3'd0;
//         READREG2 = 3'd4;
        
//         #7
//         RESET = 1'b0;
        
//         #3
//         WRITEREG = 3'd2;
//         WRITEDATA = 8'd95;
//         WRITEENABLE = 1'b1;
        
//         #9
//         WRITEENABLE = 1'b0;
        
//         #1
//         READREG1 = 3'd2;
        
//         #9
//         WRITEREG = 3'd1;
//         WRITEDATA = 8'd28;
//         WRITEENABLE = 1'b1;
//         READREG1 = 3'd1;
        
//         #10
//         WRITEENABLE = 1'b0;
        
//         #10
//         WRITEREG = 3'd4;
//         WRITEDATA = 8'd6;
//         WRITEENABLE = 1'b1;
        
//         #10
//         WRITEDATA = 8'd15;
//         WRITEENABLE = 1'b1;
        
//         #10
//         WRITEENABLE = 1'b0;
        
//         #6
//         WRITEREG = 3'd1;
//         WRITEDATA = 8'd50;
//         WRITEENABLE = 1'b1;
        
//         #5
//         WRITEENABLE = 1'b0;
        
//         #10
//         $finish;
//     end
    
//     // clock signal generation
//     always
//         #5 CLK = ~CLK;
        
// endmodule


//register file module
module reg_file(IN,OUT1,OUT2,INADDRESS,OUT1ADDRESS,OUT2ADDRESS, WRITE, CLK, RESET);

	// Port declarations
	output wire signed [7:0] OUT1, OUT2;
	input [2:0] INADDRESS, OUT1ADDRESS, OUT2ADDRESS;
    input signed [7:0] IN;
    input WRITE, RESET, CLK;

    integer i;

    // declaring internal registers
    reg signed [7:0] registers [7:0];//regdata0, regdata1, regdata2, regdata3, regdata4, regdata5, regdata6, regdata7;


    //synchroneous writing and reseting
    always @(posedge CLK) 
    begin
        if (WRITE == 1'b1 && RESET== 1'b0) begin    //if RESET=0 and WRITE enable is high then write the registers 
            #1 registers [INADDRESS] = IN;          //one unit, time delay for writing   
        end

        if (RESET == 1'b1) begin                    //if RESET is set to 1 clear all the registers
            for( i=0;i<8;i=i+1) begin               //one unit, time delay
                registers [i] <= #1 8'b0;           //assigning zero to every register
            end
        end 
    end

    //output the register OUT1 values asynchroneously
    //whenever a register changes OUT1 should be change respectivly
    
    assign #2 OUT1 = registers[OUT1ADDRESS]; 
    assign #2 OUT2 = registers[OUT2ADDRESS];                                      

	initial
	begin
		#5;
		$display("\n\t\t\t___________________________________________________");
		$display("\n\t\t\t CHANGE OF REGISTER CONTENT STARTING FROM TIME #5");
		$display("\n\t\t\t___________________________________________________\n");
		$display("\t\ttime\treg0\treg1\treg2\treg3\treg4\treg5\treg6\treg7");
		$display("\t\t____________________________________________________________________");
		$monitor($time, "\t%d\t%d\t%d\t%d\t%d\t%d\t%d\t%d",registers[0],registers[1],registers[2],registers[3],registers[4],registers[5],registers[6],registers[7]);
	end
    

endmodule

Lab 5_3/cpu_tb.v
// Computer Architecture (CO224) - Lab 05
// Design: Testbench of Integrated CPU of Simple Processor
// Author: Isuru Nawinne

`include "ALU.v"			//Include the module ALU
`include "REG.v"		    //Include the module regfile

module cpu_tb;

    reg CLK, RESET;
    wire [31:0] PC;
    wire [31:0] INSTRUCTION;
    
    /* 
    ------------------------
     SIMPLE INSTRUCTION MEM
    ------------------------
    */
    
    // TODO: Initialize an array of registers (8x1024) named 'instr_mem' to be used as instruction memory
    reg [7:0] instr_mem [0:1024];
    // TODO: Create combinational logic to support CPU instruction fetching, given the Program Counter(PC) value 
    //       (make sure you include the delay for instruction fetching here)
    
    assign #2 INSTRUCTION[7:0] = instr_mem[PC];
    assign #2 INSTRUCTION[15:8] = instr_mem[PC+1];
    assign #2 INSTRUCTION[23:16] = instr_mem[PC+2];
    assign #2 INSTRUCTION[31:24]= instr_mem[PC+3];
    	

    initial
    begin
        // Initialize instruction memory with the set of instructions you need execute on CPU
        
        // METHOD 1: manually loading instructions to instr_mem
        //{instr_mem[10'd3], instr_mem[10'd2], instr_mem[10'd1], instr_mem[10'd0]} = 32'b00000000000001000000000000000101;
        //{instr_mem[10'd7], instr_mem[10'd6], instr_mem[10'd5], instr_mem[10'd4]} = 32'b00000000000000100000000000001001;
        //{instr_mem[10'd11], instr_mem[10'd10], instr_mem[10'd9], instr_mem[10'd8]} = 32'b00000010000001100000010000000010;
        
        // METHOD 2: loading instr_mem content from instr_mem.mem file
        $readmemb("instr_mem.mem", instr_mem);
    end
    
    /* 
    -----
     CPU
    -----
    */
    cpu mycpu(PC, INSTRUCTION, CLK, RESET);

    initial
    begin
    
        // generate files needed to plot the waveform using GTKWave
        $dumpfile("cpu_wavedata.vcd");
		$dumpvars(0, cpu_tb);
        
        CLK = 1'b0;

        #3
        RESET = 1'b1;
        #3
        RESET = 1'b0;
        
        // TODO: Reset the CPU (by giving a pulse to RESET signal) to start the program execution
        
        // finish simulation after some time
        #500
        $finish;
        
    end
    
    // clock signal generation
    always
        #4 CLK = ~CLK;
        
endmodule

module cpu(PC, INSTRUCTION, CLK, RESET);
    input CLK, RESET, ZERO;
    input [31:0] INSTRUCTION;   //32 bit instruction
    output reg [31:0] PC;       //32 bit programe counter

    wire writeEnable,addOrSubSelect, imediateSelect, jump, branch;
    wire [2:0] WRITEREG,READREG1,READREG2,ALUOP;
    wire [7:0] OPCODE,REGOUT1,REGOUT2, ALURESULT, IMMEDIATE, negative, mux1out,mux2out;
    wire [31:0] newPC, temp1PC, temp2PC, offset, extended_offset;
    wire beq, offset_select;
    //instruction fetching 
    assign    WRITEREG=   INSTRUCTION[18:16];
    assign    READREG1=   INSTRUCTION[10:8];
    assign    READREG2=   INSTRUCTION[2:0]; 
    assign    OPCODE  =   INSTRUCTION[31:24];
    assign    IMMEDIATE=  INSTRUCTION[7:0];

    //find the offset corosponding to the jump and branch vlues
    assign offset = INSTRUCTION[23:16];
    assign extended_offset = { {22{offset[7]}}, offset, 2'b00};

    control_unit controlUnit(OPCODE,writeEnable,ALUOP,immediateSelect,suboraddSelect, jump,branch);
    reg_file regfile(ALURESULT,REGOUT1,REGOUT2,WRITEREG,READREG1,READREG2, writeEnable, CLK, RESET);

    assign #1 negative = ~REGOUT2 + 1;

    assign #1 temp1PC = PC + 4 ;
    assign #2 temp2PC = PC + 4 + extended_offset;


    mux8bit2_1 mux1(REGOUT2,negative,suboraddSelect,mux1out);
    mux8bit2_1 mux2(IMMEDIATE,mux1out,immediateSelect,mux2out);

    alu myalu(REGOUT1,mux2out, ALURESULT, ALUOP,ZERO);

    //offset enable signal
    and a(beq,branch,ZERO);
    or o(offset_select,beq,jump);

    mux32bit2_1 pc_update(temp1PC,temp2PC,offset_select,newPC);
    

    //at positive edge of the clock PC updating or reseting
    always @ (posedge CLK) begin
        if(RESET==1'b1) begin
           #1 PC =  32'd0;
        end else begin
           #1 PC=  newPC;

        end
    end

endmodule


module control_unit(OPCODE,writeEnable,ALUOP,immediateSelect,suboraddSelect, jump,branch);
    // port declaration
    input [7:0] OPCODE;
    output reg suboraddSelect, immediateSelect, writeEnable, jump,branch;
    output reg [2:0] ALUOP;

    always @ (OPCODE) begin
        case (OPCODE)
            8'd0: {branch, jump, ALUOP, suboraddSelect, immediateSelect, writeEnable} <= #1 8'b0_0_000_0_0_1;    // loadi
            8'd1: {branch, jump, ALUOP, suboraddSelect, immediateSelect, writeEnable} <= #1 8'b0_0_000_0_1_1;    // mov
            8'd2: {branch, jump, ALUOP, suboraddSelect, immediateSelect, writeEnable} <= #1 8'b0_0_001_0_1_1;    // add
            8'd3: {branch, jump, ALUOP, suboraddSelect, immediateSelect, writeEnable} <= #1 8'b0_0_001_1_1_1;    // sub
            8'd4: {branch, jump, ALUOP, suboraddSelect, immediateSelect, writeEnable} <= #1 8'b0_0_010_0_1_1;    // and
            8'd5: {branch, jump, ALUOP, suboraddSelect, immediateSelect, writeEnable} <= #1 8'b0_0_011_0_1_1;    // or
            8'd6: {branch, jump, ALUOP, suboraddSelect, immediateSelect, writeEnable} <= #1 8'b0_1_011_0_1_1;    // jump
            8'd7: {branch, jump, ALUOP, suboraddSelect, immediateSelect, writeEnable} <= #1 8'b1_0_011_0_1_1;    // branch
        endcase
    end

endmodule



module mux8bit2_1(IN1,IN2,SEL,OUT);
    input [7:0]IN1,IN2;
    input SEL;
    output reg [7:0] OUT;

    always @(IN1,IN2,SEL) begin
        if(SEL)begin
            OUT=IN2;
        end else begin
            OUT=IN1;
        end

    end

endmodule

module mux32bit2_1(IN1,IN2,SEL,OUT);
    input [31:0]IN1,IN2;
    input SEL;
    output reg [31:0] OUT;

    always @(IN1,IN2,SEL) begin
        if(SEL)begin
            OUT=IN2;
        end else begin
            OUT=IN1;
        end
    end
endmodule

Lab 5_3/cpu_wavedata.vcd
$date
	Tue Feb  1 22:53:13 2022
$end
$version
	Icarus Verilog
$end
$timescale
	1s
$end
$scope module cpu_tb $end
$var wire 32 ! PC [31:0] $end
$var wire 32 " INSTRUCTION [31:0] $end
$var reg 1 # CLK $end
$var reg 1 $ RESET $end
$scope module mycpu $end
$var wire 1 # CLK $end
$var wire 32 % INSTRUCTION [31:0] $end
$var wire 1 $ RESET $end
$var wire 1 & beq $end
$var wire 1 ' offset_select $end
$var wire 1 ( writeEnable $end
$var wire 32 ) temp2PC [31:0] $end
$var wire 32 * temp1PC [31:0] $end
$var wire 1 + suboraddSelect $end
$var wire 32 , offset [31:0] $end
$var wire 32 - newPC [31:0] $end
$var wire 8 . negative [7:0] $end
$var wire 8 / mux2out [7:0] $end
$var wire 8 0 mux1out [7:0] $end
$var wire 1 1 jump $end
$var wire 1 2 immediateSelect $end
$var wire 32 3 extended_offset [31:0] $end
$var wire 1 4 branch $end
$var wire 1 5 ZERO $end
$var wire 3 6 WRITEREG [2:0] $end
$var wire 8 7 REGOUT2 [7:0] $end
$var wire 8 8 REGOUT1 [7:0] $end
$var wire 3 9 READREG2 [2:0] $end
$var wire 3 : READREG1 [2:0] $end
$var wire 8 ; OPCODE [7:0] $end
$var wire 8 < IMMEDIATE [7:0] $end
$var wire 8 = ALURESULT [7:0] $end
$var wire 3 > ALUOP [2:0] $end
$var reg 32 ? PC [31:0] $end
$scope module controlUnit $end
$var wire 8 @ OPCODE [7:0] $end
$var reg 3 A ALUOP [2:0] $end
$var reg 1 4 branch $end
$var reg 1 2 immediateSelect $end
$var reg 1 1 jump $end
$var reg 1 + suboraddSelect $end
$var reg 1 ( writeEnable $end
$upscope $end
$scope module mux1 $end
$var wire 8 B IN2 [7:0] $end
$var wire 1 + SEL $end
$var wire 8 C IN1 [7:0] $end
$var reg 8 D OUT [7:0] $end
$upscope $end
$scope module mux2 $end
$var wire 8 E IN1 [7:0] $end
$var wire 8 F IN2 [7:0] $end
$var wire 1 2 SEL $end
$var reg 8 G OUT [7:0] $end
$upscope $end
$scope module myalu $end
$var wire 8 H DATA2 [7:0] $end
$var wire 8 I RESULT [7:0] $end
$var wire 3 J SELECT [2:0] $end
$var wire 1 5 ZERO $end
$var wire 8 K RESULT4 [7:0] $end
$var wire 8 L RESULT3 [7:0] $end
$var wire 8 M RESULT2 [7:0] $end
$var wire 8 N RESULT1 [7:0] $end
$var wire 8 O DATA1 [7:0] $end
$var reg 8 P out [7:0] $end
$scope module a2 $end
$var wire 8 Q DATA2 [7:0] $end
$var wire 8 R RESULT [7:0] $end
$var wire 8 S DATA1 [7:0] $end
$var reg 1 5 ZERO $end
$upscope $end
$scope module a3 $end
$var wire 8 T DATA2 [7:0] $end
$var wire 8 U RESULT [7:0] $end
$var wire 8 V DATA1 [7:0] $end
$upscope $end
$scope module f $end
$var wire 8 W DATA2 [7:0] $end
$var wire 8 X RESULT [7:0] $end
$upscope $end
$scope module o1 $end
$var wire 8 Y DATA2 [7:0] $end
$var wire 8 Z RESULT [7:0] $end
$var wire 8 [ DATA1 [7:0] $end
$upscope $end
$upscope $end
$scope module pc_update $end
$var wire 32 \ IN1 [31:0] $end
$var wire 32 ] IN2 [31:0] $end
$var wire 1 ' SEL $end
$var reg 32 ^ OUT [31:0] $end
$upscope $end
$scope module regfile $end
$var wire 1 # CLK $end
$var wire 8 _ IN [7:0] $end
$var wire 3 ` INADDRESS [2:0] $end
$var wire 8 a OUT1 [7:0] $end
$var wire 3 b OUT1ADDRESS [2:0] $end
$var wire 8 c OUT2 [7:0] $end
$var wire 3 d OUT2ADDRESS [2:0] $end
$var wire 1 $ RESET $end
$var wire 1 ( WRITE $end
$var integer 32 e i [31:0] $end
$upscope $end
$upscope $end
$upscope $end
$enddefinitions $end
#0
$dumpvars
bx e
bx d
bx c
bx b
bx a
bx `
bx _
bx ^
bx ]
bx \
bx [
bx Z
bx Y
bx X
bx W
bx V
bx U
bx T
bx S
bx R
bx Q
bx P
bx O
bx N
bx M
bx L
bx K
bx J
bx I
bx H
bx G
bx F
bx E
bx D
bx C
bx B
bx A
bx @
bx ?
bx >
bx =
bx <
bx ;
bx :
bx 9
bx 8
bx 7
bx 6
x5
x4
b0xxxxxxxx00 3
x2
x1
bx 0
bx /
bx .
bx -
b0xxxxxxxx ,
x+
bx *
bx )
x(
x'
x&
bx %
x$
0#
bx "
bx !
$end
#3
1$
#4
b1000 e
1#
#5
b0 !
b0 ?
#6
b100 -
b100 ^
b100 *
b100 \
0$
#7
b10000 3
b101 /
b101 G
b101 H
b101 Q
b101 T
b101 W
b101 Y
b0 ;
b0 @
b100 6
b100 `
b100 ,
b0 :
b0 b
b101 9
b101 d
b101 <
b101 E
b1000000000000000101 "
b1000000000000000101 %
#8
0'
0&
b101 =
b101 I
b101 _
b101 P
04
01
b0 >
b0 A
b0 J
0+
02
1(
b0x0x L
b0x0x U
bx1x1 K
bx1x1 Z
b101 N
b101 X
0#
#9
b0 0
b0 D
b0 F
b10100 )
b10100 ]
b0 8
b0 O
b0 S
b0 V
b0 [
b0 a
b0 7
b0 C
b0 c
#10
b101 K
b101 Z
b0 L
b0 U
b0 .
b0 B
#11
05
b101 M
b101 R
#12
1#
#13
b100 !
b100 ?
#14
b1000 -
b1000 ^
b1000 *
b1000 \
#15
b1000 3
b1001 /
b1001 G
b1001 H
b1001 Q
b1001 T
b1001 W
b1001 Y
b10 6
b10 `
b10 ,
b1 9
b1 d
b1001 <
b1001 E
b11000 )
b11000 ]
b100000000000001001 "
b100000000000001001 %
#16
b1001 =
b1001 I
b1001 _
b1001 P
b1001 K
b1001 Z
b1001 N
b1001 X
0#
#17
b10000 )
b10000 ]
b1001 M
b1001 R
#20
1#
#21
b1000 !
b1000 ?
#22
b1100 -
b1100 ^
b1100 *
b1100 \
#23
b11000 3
b10 /
b10 G
b10 H
b10 Q
b10 T
b10 W
b10 Y
b10 ;
b10 @
b110 6
b110 `
b110 ,
b100 :
b100 b
b10 9
b10 d
b10 <
b10 E
b10100 )
b10100 ]
b10000001100000010000000010 "
b10000001100000010000000010 %
#24
b0 /
b0 G
b0 H
b0 Q
b0 T
b0 W
b0 Y
b1 >
b1 A
b1 J
12
b1001 =
b1001 I
b1001 _
b1001 P
b10 K
b10 Z
b10 N
b10 X
0#
#25
b1001 /
b1001 G
b1001 H
b1001 Q
b1001 T
b1001 W
b1001 Y
b1001 0
b1001 D
b1001 F
b0 K
b0 Z
b0 N
b0 X
b100100 )
b100100 ]
b101 8
b101 O
b101 S
b101 V
b101 [
b101 a
b1001 7
b1001 C
b1001 c
#26
b1 L
b1 U
b1001 N
b1001 X
b1101 K
b1101 Z
b11110111 .
b11110111 B
#27
b1110 =
b1110 I
b1110 _
b1110 P
b1110 M
b1110 R
#28
1#
#29
b1100 !
b1100 ?
#30
b10000 -
b10000 ^
b10000 *
b10000 \
#31
b0 3
b1 ;
b1 @
b0 6
b0 `
b0 ,
b0 :
b0 b
b110 9
b110 d
b110 <
b110 E
b101000 )
b101000 ]
b1000000000000000000000110 "
b1000000000000000000000110 %
#32
b1001 =
b1001 I
b1001 _
b1001 P
b0 >
b0 A
b0 J
0#
#33
b1110 /
b1110 G
b1110 H
b1110 Q
b1110 T
b1110 W
b1110 Y
b1110 0
b1110 D
b1110 F
b10000 )
b10000 ]
b0 8
b0 O
b0 S
b0 V
b0 [
b0 a
b1110 7
b1110 C
b1110 c
#34
b1110 =
b1110 I
b1110 _
b1110 P
b1110 N
b1110 X
b1110 K
b1110 Z
b0 L
b0 U
b11110010 .
b11110010 B
#36
1#
#37
b10000 !
b10000 ?
#38
b10100 -
b10100 ^
b10100 *
b10100 \
#39
b100 3
b0 ;
b0 @
b1 6
b1 `
b1 ,
b1 9
b1 d
b1 <
b1 E
b10100 )
b10100 ]
b10000000000000001 "
b10000000000000001 %
b1110 8
b1110 O
b1110 S
b1110 V
b1110 [
b1110 a
#40
b1 /
b1 G
b1 H
b1 Q
b1 T
b1 W
b1 Y
02
b1110 L
b1110 U
0#
#41
b1 =
b1 I
b1 _
b1 P
b0 0
b0 D
b0 F
b0 L
b0 U
b1111 K
b1111 Z
b1 N
b1 X
b11000 )
b11000 ]
b0 7
b0 C
b0 c
#42
b0 .
b0 B
b1111 M
b1111 R
#44
1#
#45
b10100 !
b10100 ?
#46
b11000 -
b11000 ^
b11000 *
b11000 \
#47
b1000 3
b1 0
b1 D
b1 F
b10 ;
b10 @
b10 6
b10 `
b10 ,
b10 :
b10 b
b1 7
b1 C
b1 c
b11100 )
b11100 ]
b10000000100000001000000001 "
b10000000100000001000000001 %
#48
b1111 =
b1111 I
b1111 _
b1111 P
b1 >
b1 A
b1 J
12
b11111111 .
b11111111 B
0#
#49
b100000 )
b100000 ]
b1001 8
b1001 O
b1001 S
b1001 V
b1001 [
b1001 a
#50
b1001 K
b1001 Z
b1 L
b1 U
#51
b1010 =
b1010 I
b1010 _
b1010 P
b1010 M
b1010 R
#52
1#
#53
b11000 !
b11000 ?
#54
b11100 -
b11100 ^
b11100 *
b11100 \
#55
b1100 3
b11 ;
b11 @
b11 6
b11 `
b11 ,
b100 9
b100 d
b100 <
b100 E
b100100 )
b100100 ]
b11000000110000001000000100 "
b11000000110000001000000100 %
b1010 8
b1010 O
b1010 S
b1010 V
b1010 [
b1010 a
#56
b11111111 /
b11111111 G
b11111111 H
b11111111 Q
b11111111 T
b11111111 W
b11111111 Y
b11111111 0
b11111111 D
b11111111 F
1+
b1011 K
b1011 Z
b0 L
b0 U
0#
#57
b1010 L
b1010 U
b11111111 K
b11111111 Z
b11111111 N
b11111111 X
b101000 )
b101000 ]
b101 7
b101 C
b101 c
#58
b11111011 /
b11111011 G
b11111011 H
b11111011 Q
b11111011 T
b11111011 W
b11111011 Y
b11111011 0
b11111011 D
b11111011 F
b1001 =
b1001 I
b1001 _
b1001 P
b11111011 .
b11111011 B
b1001 M
b1001 R
#59
b11111011 K
b11111011 Z
b11111011 N
b11111011 X
#60
b101 =
b101 I
b101 _
b101 P
b101 M
b101 R
1#
#61
b11100 !
b11100 ?
#62
b100000 -
b100000 ^
b100000 *
b100000 \
#63
b0xxxxxxxx00 3
bx ;
bx @
bx 6
bx `
b0xxxxxxxx ,
bx :
bx b
bx 9
bx d
bx <
bx E
b101100 )
b101100 ]
bx "
bx %
#64
0#
#65
bx )
bx ]
bx 8
bx O
bx S
bx V
bx [
bx a
bx 7
bx C
bx c
#66
bx /
bx G
bx H
bx Q
bx T
bx W
bx Y
bx 0
bx D
bx F
b11111x11 K
b11111x11 Z
bx0xx L
bx0xx U
bx .
bx B
#67
bx =
bx I
bx _
bx P
bx L
bx U
bx K
bx Z
bx N
bx X
bx M
bx R
#68
1#
#69
b100000 !
b100000 ?
#70
b100100 -
b100100 ^
b100100 *
b100100 \
#72
0#
#76
1#
#77
b100100 !
b100100 ?
#78
b101000 -
b101000 ^
b101000 *
b101000 \
#80
0#
#84
1#
#85
b101000 !
b101000 ?
#86
b101100 -
b101100 ^
b101100 *
b101100 \
#88
0#
#92
1#
#93
b101100 !
b101100 ?
#94
b110000 -
b110000 ^
b110000 *
b110000 \
#96
0#
#100
1#
#101
b110000 !
b110000 ?
#102
b110100 -
b110100 ^
b110100 *
b110100 \
#104
0#
#108
1#
#109
b110100 !
b110100 ?
#110
b111000 -
b111000 ^
b111000 *
b111000 \
#112
0#
#116
1#
#117
b111000 !
b111000 ?
#118
b111100 -
b111100 ^
b111100 *
b111100 \
#120
0#
#124
1#
#125
b111100 !
b111100 ?
#126
b1000000 -
b1000000 ^
b1000000 *
b1000000 \
#128
0#
#132
1#
#133
b1000000 !
b1000000 ?
#134
b1000100 -
b1000100 ^
b1000100 *
b1000100 \
#136
0#
#140
1#
#141
b1000100 !
b1000100 ?
#142
b1001000 -
b1001000 ^
b1001000 *
b1001000 \
#144
0#
#148
1#
#149
b1001000 !
b1001000 ?
#150
b1001100 -
b1001100 ^
b1001100 *
b1001100 \
#152
0#
#156
1#
#157
b1001100 !
b1001100 ?
#158
b1010000 -
b1010000 ^
b1010000 *
b1010000 \
#160
0#
#164
1#
#165
b1010000 !
b1010000 ?
#166
b1010100 -
b1010100 ^
b1010100 *
b1010100 \
#168
0#
#172
1#
#173
b1010100 !
b1010100 ?
#174
b1011000 -
b1011000 ^
b1011000 *
b1011000 \
#176
0#
#180
1#
#181
b1011000 !
b1011000 ?
#182
b1011100 -
b1011100 ^
b1011100 *
b1011100 \
#184
0#
#188
1#
#189
b1011100 !
b1011100 ?
#190
b1100000 -
b1100000 ^
b1100000 *
b1100000 \
#192
0#
#196
1#
#197
b1100000 !
b1100000 ?
#198
b1100100 -
b1100100 ^
b1100100 *
b1100100 \
#200
0#
#204
1#
#205
b1100100 !
b1100100 ?
#206
b1101000 -
b1101000 ^
b1101000 *
b1101000 \
#208
0#
#212
1#
#213
b1101000 !
b1101000 ?
#214
b1101100 -
b1101100 ^
b1101100 *
b1101100 \
#216
0#
#220
1#
#221
b1101100 !
b1101100 ?
#222
b1110000 -
b1110000 ^
b1110000 *
b1110000 \
#224
0#
#228
1#
#229
b1110000 !
b1110000 ?
#230
b1110100 -
b1110100 ^
b1110100 *
b1110100 \
#232
0#
#236
1#
#237
b1110100 !
b1110100 ?
#238
b1111000 -
b1111000 ^
b1111000 *
b1111000 \
#240
0#
#244
1#
#245
b1111000 !
b1111000 ?
#246
b1111100 -
b1111100 ^
b1111100 *
b1111100 \
#248
0#
#252
1#
#253
b1111100 !
b1111100 ?
#254
b10000000 -
b10000000 ^
b10000000 *
b10000000 \
#256
0#
#260
1#
#261
b10000000 !
b10000000 ?
#262
b10000100 -
b10000100 ^
b10000100 *
b10000100 \
#264
0#
#268
1#
#269
b10000100 !
b10000100 ?
#270
b10001000 -
b10001000 ^
b10001000 *
b10001000 \
#272
0#
#276
1#
#277
b10001000 !
b10001000 ?
#278
b10001100 -
b10001100 ^
b10001100 *
b10001100 \
#280
0#
#284
1#
#285
b10001100 !
b10001100 ?
#286
b10010000 -
b10010000 ^
b10010000 *
b10010000 \
#288
0#
#292
1#
#293
b10010000 !
b10010000 ?
#294
b10010100 -
b10010100 ^
b10010100 *
b10010100 \
#296
0#
#300
1#
#301
b10010100 !
b10010100 ?
#302
b10011000 -
b10011000 ^
b10011000 *
b10011000 \
#304
0#
#308
1#
#309
b10011000 !
b10011000 ?
#310
b10011100 -
b10011100 ^
b10011100 *
b10011100 \
#312
0#
#316
1#
#317
b10011100 !
b10011100 ?
#318
b10100000 -
b10100000 ^
b10100000 *
b10100000 \
#320
0#
#324
1#
#325
b10100000 !
b10100000 ?
#326
b10100100 -
b10100100 ^
b10100100 *
b10100100 \
#328
0#
#332
1#
#333
b10100100 !
b10100100 ?
#334
b10101000 -
b10101000 ^
b10101000 *
b10101000 \
#336
0#
#340
1#
#341
b10101000 !
b10101000 ?
#342
b10101100 -
b10101100 ^
b10101100 *
b10101100 \
#344
0#
#348
1#
#349
b10101100 !
b10101100 ?
#350
b10110000 -
b10110000 ^
b10110000 *
b10110000 \
#352
0#
#356
1#
#357
b10110000 !
b10110000 ?
#358
b10110100 -
b10110100 ^
b10110100 *
b10110100 \
#360
0#
#364
1#
#365
b10110100 !
b10110100 ?
#366
b10111000 -
b10111000 ^
b10111000 *
b10111000 \
#368
0#
#372
1#
#373
b10111000 !
b10111000 ?
#374
b10111100 -
b10111100 ^
b10111100 *
b10111100 \
#376
0#
#380
1#
#381
b10111100 !
b10111100 ?
#382
b11000000 -
b11000000 ^
b11000000 *
b11000000 \
#384
0#
#388
1#
#389
b11000000 !
b11000000 ?
#390
b11000100 -
b11000100 ^
b11000100 *
b11000100 \
#392
0#
#396
1#
#397
b11000100 !
b11000100 ?
#398
b11001000 -
b11001000 ^
b11001000 *
b11001000 \
#400
0#
#404
1#
#405
b11001000 !
b11001000 ?
#406
b11001100 -
b11001100 ^
b11001100 *
b11001100 \
#408
0#
#412
1#
#413
b11001100 !
b11001100 ?
#414
b11010000 -
b11010000 ^
b11010000 *
b11010000 \
#416
0#
#420
1#
#421
b11010000 !
b11010000 ?
#422
b11010100 -
b11010100 ^
b11010100 *
b11010100 \
#424
0#
#428
1#
#429
b11010100 !
b11010100 ?
#430
b11011000 -
b11011000 ^
b11011000 *
b11011000 \
#432
0#
#436
1#
#437
b11011000 !
b11011000 ?
#438
b11011100 -
b11011100 ^
b11011100 *
b11011100 \
#440
0#
#444
1#
#445
b11011100 !
b11011100 ?
#446
b11100000 -
b11100000 ^
b11100000 *
b11100000 \
#448
0#
#452
1#
#453
b11100000 !
b11100000 ?
#454
b11100100 -
b11100100 ^
b11100100 *
b11100100 \
